{
  "subjectId": "ba_constitution_v5",
  "subjectTitle": "भारत का संविधान - Class 5 (संघ एवं उसका राज्य क्षेत्र)",
  "topics": [
    {
      "title": "भारत का संघ, नए राज्यों का प्रवेश एवं पुनर्गठन (Class-5)",
      "slides": [
        "• **भाग 1 (अनुच्छेद 1-4):** संविधान का भाग 1 'संघ और उसके राज्य क्षेत्रों' से संबंधित है। \n1. **अनुच्छेद 1:** भारत, जो कि 'इण्डिया' है, राज्यों का एक संघ (Union of States) होगा। यहाँ 'यूनियन' शब्द का प्रयोग किया गया है, जिसका अर्थ है कि किसी भी राज्य को संघ से अलग होने का अधिकार नहीं है। \n2. **अनुच्छेद 2:** संसद को शक्ति दी गई है कि वह नए राज्यों को भारत के संघ में शामिल कर सके या नए राज्यों की स्थापना कर सके।",
        "• **राज्यों का पुनर्गठन (अनुच्छेद 3):** संसद किसी भी राज्य के नाम, सीमा या क्षेत्र में परिवर्तन कर सकती है। \n1. **प्रक्रिया:** ऐसा विधेयक राष्ट्रपति की सिफारिश पर ही संसद में पेश किया जाता है। \n2. **बहुमत:** नए राज्यों के निर्माण के लिए संसद में 'साधारण बहुमत' (Simple Majority) की आवश्यकता होती है। \n• **अनुच्छेद 4:** अनुच्छेद 2 और 3 के तहत किए गए बदलावों को अनुच्छेद 368 के तहत 'संविधान संशोधन' नहीं माना जाएगा।",
        "• **भाषाई आधार पर पुनर्गठन:** \n1. **धर आयोग (1948):** राज्यों के पुनर्गठन के लिए भाषा के स्थान पर प्रशासनिक सुविधा को आधार माना। \n2. **JVP समिति:** नेहरू, पटेल और सीता रमैया की इस समिति ने भी भाषाई आधार को खारिज किया। \n3. **आंध्र प्रदेश (1953):** पोट्टी श्रीरामुलु की 56 दिन की भूख हड़ताल के बाद मृत्यु होने पर, आंध्र प्रदेश भाषा के आधार पर बनने वाला 'पहला राज्य' बना।",
        "\n• **राज्य पुनर्गठन अधिनियम 1956:** \n- फजल अली आयोग की सिफारिश पर 7वें संविधान संशोधन (1956) द्वारा भारत को 14 राज्यों और 6 केंद्रशासित प्रदेशों में विभाजित किया गया। \n- वर्तमान में भारत में कुल **28 राज्य और 8 केंद्रशासित प्रदेश** हैं।"
      ],
      "questions": [
        { "questionText": "संविधान के अनुच्छेद 1 में भारत को क्या कहा गया है?", "options": ["राज्यों का समूह", "राज्यों का संघ (Union)", "परिसंघ", "एकात्मक राज्य"], "correctAnswer": "राज्यों का संघ (Union)" },
        { "questionText": "नए राज्यों के प्रवेश या स्थापना की शक्ति किसके पास है?", "options": ["राष्ट्रपति", "प्रधानमंत्री", "संसद", "सुप्रीम कोर्ट"], "correctAnswer": "संसद" },
        { "questionText": "संसद किसी राज्य के नाम या सीमा में परिवर्तन किस अनुच्छेद के तहत करती है?", "options": ["अनुच्छेद 1", "अनुच्छेद 2", "अनुच्छेद 3", "अनुच्छेद 4"], "correctAnswer": "अनुच्छेद 3" },
        { "questionText": "भाषाई आधार पर गठित होने वाला भारत का प्रथम राज्य कौन सा था?", "options": ["आंध्र प्रदेश", "गुजरात", "हरियाणा", "पंजाब"], "correctAnswer": "आंध्र प्रदेश" },
        { "questionText": "राज्य पुनर्गठन आयोग (1953) के अध्यक्ष कौन थे?", "options": ["एस.के. धर", "फजल अली", "हृदयनाथ कुंजरू", "के.एम. पाणिक्कर"], "correctAnswer": "फजल अली" },
        { "questionText": "1956 के पुनर्गठन के बाद भारत में कितने राज्य और केंद्रशासित प्रदेश थे?", "options": ["14 राज्य, 6 UT", "15 राज्य, 7 UT", "28 राज्य, 8 UT", "14 राज्य, 5 UT"], "correctAnswer": "14 राज्य, 6 UT" },
        { "questionText": "संसद में नए राज्यों के निर्माण के लिए किस प्रकार के बहुमत की आवश्यकता होती है?", "options": ["विशेष बहुमत", "साधारण बहुमत", "पूर्ण बहुमत", "दो-तिहाई बहुमत"], "correctAnswer": "साधारण बहुमत" },
        { "questionText": "सिक्किम को किस वर्ष भारत का पूर्ण राज्य बनाया गया था?", "options": ["1971", "1974", "1975", "1987"], "correctAnswer": "1975" },
        { "questionText": "आंध्र प्रदेश का गठन किस वर्ष हुआ था?", "options": ["1950", "1953", "1956", "1960"], "correctAnswer": "1953" },
        { "questionText": "JVP समिति में कौन शामिल नहीं था?", "options": ["जवाहरलाल नेहरू", "वल्लभ भाई पटेल", "पट्टाभि सीता रमैया", "फजल अली"], "correctAnswer": "फजल अली" },
        { "questionText": "वर्तमान में भारत में कुल कितने राज्य हैं?", "options": ["27", "28", "29", "30"], "correctAnswer": "28" },
        { "questionText": "वर्तमान में भारत में केंद्रशासित प्रदेशों (UT) की कुल संख्या कितनी है?", "options": ["7", "8", "9", "6"], "correctAnswer": "8" },
        { "questionText": "तेलंगाना राज्य का गठन कब हुआ था?", "options": ["1 नवंबर 2000", "2 जून 2014", "31 अक्टूबर 2019", "15 अगस्त 1947"], "correctAnswer": "2 जून 2014" },
        { "questionText": "किस राज्य के नाम में परिवर्तन के लिए किसकी पूर्व अनुमति आवश्यक है?", "options": ["संसद", "प्रधानमंत्री", "राष्ट्रपति", "राज्यपाल"], "correctAnswer": "राष्ट्रपति" },
        { "questionText": "गोवा को किस वर्ष राज्य का दर्जा दिया गया था?", "options": ["1961", "1971", "1987", "1975"], "correctAnswer": "1987" },
        { "questionText": "जम्मू-कश्मीर और लद्दाख को केंद्रशासित प्रदेश कब बनाया गया?", "options": ["2014", "2017", "2019", "2020"], "correctAnswer": "2019" },
        { "questionText": "फजल अली आयोग में कुल कितने सदस्य थे?", "options": ["2", "3", "4", "5"], "correctAnswer": "3" },
        { "questionText": "संविधान का भाग 1 किस अनुच्छेद से किस अनुच्छेद तक है?", "options": ["1 से 4", "5 से 11", "12 से 35", "36 से 51"], "correctAnswer": "1 से 4" },
        { "questionText": "वर्ष 2000 में गठित होने वाला राज्य कौन सा नहीं है?", "options": ["छत्तीसगढ़", "उत्तराखंड", "झारखंड", "तेलंगाना"], "correctAnswer": "तेलंगाना" },
        { "questionText": "क्या अनुच्छेद 2 और 3 के तहत किए गए बदलाव अनुच्छेद 368 के तहत संशोधन माने जाते हैं?", "options": ["हाँ", "नहीं", "केवल कुछ मामलों में", "पता नहीं"], "correctAnswer": "नहीं" }
      ]
    }
  ]
}